com/__init__.py
com/alipay/__init__.py
com/alipay/ams/__init__.py
com/alipay/ams/api/__init__.py
com/alipay/ams/api/default_alipay_client.py
com/alipay/ams/api/exception/__init__.py
com/alipay/ams/api/exception/exception.py
com/alipay/ams/api/model/DisputeJudgedResult.py
com/alipay/ams/api/model/DisputeType.py
com/alipay/ams/api/model/__init__.py
com/alipay/ams/api/model/aba_card.py
com/alipay/ams/api/model/account_balance.py
com/alipay/ams/api/model/account_holder_type.py
com/alipay/ams/api/model/account_type.py
com/alipay/ams/api/model/acquirer_info.py
com/alipay/ams/api/model/address.py
com/alipay/ams/api/model/agreement_info.py
com/alipay/ams/api/model/amount.py
com/alipay/ams/api/model/amount_limit.py
com/alipay/ams/api/model/amount_limit_info.py
com/alipay/ams/api/model/ancillary_data.py
com/alipay/ams/api/model/antom_path_constants.py
com/alipay/ams/api/model/apple_pay_configuration.py
com/alipay/ams/api/model/association_type.py
com/alipay/ams/api/model/attachment.py
com/alipay/ams/api/model/attachment_type.py
com/alipay/ams/api/model/auth_code_form.py
com/alipay/ams/api/model/auth_meta_data.py
com/alipay/ams/api/model/authentication_channel_type.py
com/alipay/ams/api/model/authentication_type.py
com/alipay/ams/api/model/authorization_control.py
com/alipay/ams/api/model/authorization_error.py
com/alipay/ams/api/model/authorization_phase.py
com/alipay/ams/api/model/available_payment_method.py
com/alipay/ams/api/model/browser_info.py
com/alipay/ams/api/model/business_info.py
com/alipay/ams/api/model/business_type.py
com/alipay/ams/api/model/buyer.py
com/alipay/ams/api/model/cancellation_type.py
com/alipay/ams/api/model/capture_mode.py
com/alipay/ams/api/model/card.py
com/alipay/ams/api/model/card_brand.py
com/alipay/ams/api/model/card_brand_type.py
com/alipay/ams/api/model/card_info.py
com/alipay/ams/api/model/card_limit_detail.py
com/alipay/ams/api/model/card_limit_info.py
com/alipay/ams/api/model/card_payment_method_detail.py
global_open_sdk_python-1.4.26.dist-info/licenses/LICENSE
global_open_sdk_python-1.4.26.dist-info/METADATA
global_open_sdk_python-1.4.26.dist-info/WHEEL
global_open_sdk_python-1.4.26.dist-info/top_level.txt
global_open_sdk_python-1.4.26.dist-info/RECORD
