Metadata-Version: 2.4
Name: global-open-sdk-python
Version: 1.4.26
Summary: The global alipay gateway SDK for Python.
Home-page: https://github.com/alipay/global-open-sdk-python
Author: guodong.wzj
Author-email: wangzunjiao.wzj@digital-engine.com
License: MIT
Keywords: global,alipay,sdk
Platform: any
Classifier: Intended Audience :: Developers
Classifier: License :: OSI Approved :: MIT License
Classifier: Programming Language :: Python
Classifier: Programming Language :: Python :: 2.7
Classifier: Programming Language :: Python :: 3.2
Classifier: Programming Language :: Python :: 3.3
Classifier: Programming Language :: Python :: 3.4
Classifier: Programming Language :: Python :: 3.5
Classifier: Programming Language :: Python :: 3.6
Classifier: Programming Language :: Python :: 3.7
Classifier: Programming Language :: Python :: 3.8
Classifier: Programming Language :: Python :: 3.9
Classifier: Programming Language :: Python :: 3.10
Classifier: Programming Language :: Python :: 3.11
Classifier: Programming Language :: Python :: 3.12
Classifier: Topic :: Software Development
License-File: LICENSE
Requires-Dist: enum34
Requires-Dist: pytz
Requires-Dist: pycryptodome
Requires-Dist: rsa
Requires-Dist: cryptography
Dynamic: author
Dynamic: author-email
Dynamic: classifier
Dynamic: home-page
Dynamic: keywords
Dynamic: license
Dynamic: license-file
Dynamic: platform
Dynamic: requires-dist
Dynamic: summary
